{
  "last_updated":"2026-07-24 12:52:53 IST",
  "movies":[
    {
      "name":"Eka Thamai Meka",
      "slug":"eka-thamai-meka",
      "totalGross":435850.0,
      "totalTickets":507
    },
    {
      "name":"Minions & Monsters",
      "slug":"minions-monsters",
      "totalGross":998500.0,
      "totalTickets":811
    },
    {
      "name":"Room No.106",
      "slug":"room-no106",
      "totalGross":1015650.0,
      "totalTickets":1625
    },
    {
      "name":"Sooriya Sulanga",
      "slug":"sooriya-sulanga",
      "totalGross":426500.0,
      "totalTickets":880
    },
    {
      "name":"Gatta Kusthi 2",
      "slug":"gatta-kusthi-2",
      "totalGross":623750.0,
      "totalTickets":618
    },
    {
      "name":"Alpha",
      "slug":"alpha",
      "totalGross":465750.0,
      "totalTickets":321
    },
    {
      "name":"Young Washington",
      "slug":"young-washington",
      "totalGross":239950.0,
      "totalTickets":96
    },
    {
      "name":"Michael",
      "slug":"michael",
      "totalGross":622500.0,
      "totalTickets":425
    },
    {
      "name":"Backrooms",
      "slug":"backrooms",
      "totalGross":214300.0,
      "totalTickets":108
    },
    {
      "name":"Scary Movie",
      "slug":"scary-movie",
      "totalGross":34200.0,
      "totalTickets":21
    },
    {
      "name":"Love Oh Love",
      "slug":"love-oh-love",
      "totalGross":21850.0,
      "totalTickets":22
    },
    {
      "name":"Chandarege Wife",
      "slug":"chandarege-wife",
      "totalGross":59500.0,
      "totalTickets":89
    },
    {
      "name":"Dhamaal 4",
      "slug":"dhamaal-4",
      "totalGross":367950.0,
      "totalTickets":287
    },
    {
      "name":"Toy Story 5",
      "slug":"toy-story-5",
      "totalGross":311350.0,
      "totalTickets":252
    },
    {
      "name":"Cocktail 2",
      "slug":"cocktail-2",
      "totalGross":572450.0,
      "totalTickets":371
    },
    {
      "name":"Moana",
      "slug":"moana",
      "totalGross":3478450.0,
      "totalTickets":2685
    },
    {
      "name":"Oscar",
      "slug":"oscar",
      "totalGross":35700.0,
      "totalTickets":57
    },
    {
      "name":"OIC Gadafi",
      "slug":"oic-gadafi",
      "totalGross":500.0,
      "totalTickets":2
    },
    {
      "name":"The Sheep Detectives",
      "slug":"the-sheep-detectives",
      "totalGross":189700.0,
      "totalTickets":152
    },
    {
      "name":"Idhayam Murali",
      "slug":"idhayam-murali",
      "totalGross":1332550.0,
      "totalTickets":1259
    },
    {
      "name":"Supergirl",
      "slug":"supergirl",
      "totalGross":326500.0,
      "totalTickets":216
    },
    {
      "name":"Welcome To The Jungle",
      "slug":"welcome-to-the-jungle",
      "totalGross":92100.0,
      "totalTickets":37
    },
    {
      "name":"The Devil Wears Prada 2",
      "slug":"the-devil-wears-prada-2",
      "totalGross":85200.0,
      "totalTickets":34
    },
    {
      "name":"Riverstone",
      "slug":"riverstone",
      "totalGross":26300.0,
      "totalTickets":56
    },
    {
      "name":"The Voice of Hind Rajab",
      "slug":"the-voice-of-hind-rajab",
      "totalGross":0.0,
      "totalTickets":0
    },
    {
      "name":"Rajadahana",
      "slug":"rajadahana",
      "totalGross":0.0,
      "totalTickets":0
    },
    {
      "name":"Moana 2",
      "slug":"moana-2",
      "totalGross":0.0,
      "totalTickets":0
    },
    {
      "name":"Disclosure Day",
      "slug":"disclosure-day",
      "totalGross":14000.0,
      "totalTickets":12
    },
    {
      "name":"Nagabandham - The Secret Treasure",
      "slug":"nagabandham-the-secret-treasure",
      "totalGross":0.0,
      "totalTickets":0
    },
    {
      "name":"The Odyssey",
      "slug":"the-odyssey",
      "totalGross":16037950.0,
      "totalTickets":5756
    },
    {
      "name":"Evil Dead Burn",
      "slug":"evil-dead-burn",
      "totalGross":757750.0,
      "totalTickets":501
    },
    {
      "name":"My Simba",
      "slug":"my-simba",
      "totalGross":107700.0,
      "totalTickets":243
    },
    {
      "name":"Con City",
      "slug":"con-city",
      "totalGross":8800.0,
      "totalTickets":8
    },
    {
      "name":"Dark",
      "slug":"dark",
      "totalGross":7350.0,
      "totalTickets":7
    },
    {
      "name":"Abhisari",
      "slug":"abhisari",
      "totalGross":56400.0,
      "totalTickets":63
    },
    {
      "name":"Monara Wilak",
      "slug":"monara-wilak",
      "totalGross":0.0,
      "totalTickets":0
    },
    {
      "name":"Jana Nayagan",
      "slug":"jana-nayagan",
      "totalGross":19725550.0,
      "totalTickets":10753
    },
    {
      "name":"Nidhanaya",
      "slug":"nidhanaya",
      "totalGross":177600.0,
      "totalTickets":222
    },
    {
      "name":"Habeebi",
      "slug":"habeebi",
      "totalGross":3800.0,
      "totalTickets":4
    },
    {
      "name":"The Wife",
      "slug":"the-wife",
      "totalGross":0.0,
      "totalTickets":0
    },
    {
      "name":"Test LK",
      "slug":"test-lk",
      "totalGross":0.0,
      "totalTickets":0
    }
  ]
}